{
  "botName": "🍄 𝗔𝗹𝘆𝗮 𝗠𝗗",
  "totalUsers": 964,
  "totalGroups": 35,
  "totalFeatures": 3491,
  "totalCmd": 498,
  "totalChat": 498,
  "topCommands": [
    {
      "cmd": "afk",
      "count": 25
    },
    {
      "cmd": "ranked",
      "count": 23
    },
    {
      "cmd": "me",
      "count": 17
    },
    {
      "cmd": "playmoba",
      "count": 15
    },
    {
      "cmd": "rampok2",
      "count": 15
    },
    {
      "cmd": "tes",
      "count": 14
    },
    {
      "cmd": "removebg",
      "count": 13
    },
    {
      "cmd": "6285189358241",
      "count": 11
    },
    {
      "cmd": "89374091944116",
      "count": 10
    },
    {
      "cmd": "77605898313906",
      "count": 8
    }
  ],
  "ratingAvg": "10.0",
  "ratingTotal": 4,
  "uptimeSeconds": 361,
  "lastUpdated": 1773797308841
}