{
  "botName": "🍄 𝗔𝗹𝘆𝗮 𝗠𝗗",
  "totalUsers": 1084,
  "totalGroups": 38,
  "totalFeatures": 3610,
  "totalCmd": 22185,
  "totalChat": 22185,
  "topCommands": [
    {
      "cmd": "afk",
      "count": 678
    },
    {
      "cmd": "gift",
      "count": 631
    },
    {
      "cmd": "buy",
      "count": 585
    },
    {
      "cmd": "rampok2",
      "count": 550
    },
    {
      "cmd": "pap",
      "count": 542
    },
    {
      "cmd": "me",
      "count": 518
    },
    {
      "cmd": "forward",
      "count": 375
    },
    {
      "cmd": "tf",
      "count": 343
    },
    {
      "cmd": "craft",
      "count": 318
    },
    {
      "cmd": "tes",
      "count": 314
    }
  ],
  "ratingAvg": "8.3",
  "ratingTotal": 7,
  "uptimeSeconds": 1861,
  "lastUpdated": 1775818276768
}