{
  "botName": "🍄 𝗔𝗹𝘆𝗮 𝗠𝗗",
  "totalUsers": 1019,
  "totalGroups": 37,
  "totalFeatures": 3590,
  "totalCmd": 4183,
  "totalChat": 4183,
  "topCommands": [
    {
      "cmd": "afk",
      "count": 150
    },
    {
      "cmd": "rampok2",
      "count": 142
    },
    {
      "cmd": "buy",
      "count": 130
    },
    {
      "cmd": "me",
      "count": 119
    },
    {
      "cmd": "craft",
      "count": 104
    },
    {
      "cmd": "tes",
      "count": 68
    },
    {
      "cmd": "pin",
      "count": 62
    },
    {
      "cmd": "ranked",
      "count": 59
    },
    {
      "cmd": "hd",
      "count": 53
    },
    {
      "cmd": "77605898313906",
      "count": 49
    }
  ],
  "ratingAvg": "10.0",
  "ratingTotal": 5,
  "uptimeSeconds": 3661,
  "lastUpdated": 1774259936996
}