{
  "botName": "🍄 𝗔𝗹𝘆𝗮 𝗠𝗗",
  "totalUsers": 1036,
  "totalGroups": 37,
  "totalFeatures": 3607,
  "totalCmd": 7678,
  "totalChat": 7678,
  "topCommands": [
    {
      "cmd": "forward",
      "count": 327
    },
    {
      "cmd": "buy",
      "count": 283
    },
    {
      "cmd": "me",
      "count": 256
    },
    {
      "cmd": "rampok2",
      "count": 239
    },
    {
      "cmd": "pap",
      "count": 206
    },
    {
      "cmd": "afk",
      "count": 177
    },
    {
      "cmd": "gift",
      "count": 134
    },
    {
      "cmd": "craft",
      "count": 114
    },
    {
      "cmd": "carikarakter",
      "count": 92
    },
    {
      "cmd": "pin",
      "count": 89
    }
  ],
  "ratingAvg": "8.3",
  "ratingTotal": 7,
  "uptimeSeconds": 481,
  "lastUpdated": 1774360778669
}