{
  "botName": "🍄 𝗔𝗹𝘆𝗮 𝗠𝗗",
  "totalUsers": 1037,
  "totalGroups": 37,
  "totalFeatures": 3607,
  "totalCmd": 8940,
  "totalChat": 8940,
  "topCommands": [
    {
      "cmd": "forward",
      "count": 329
    },
    {
      "cmd": "buy",
      "count": 315
    },
    {
      "cmd": "me",
      "count": 277
    },
    {
      "cmd": "pap",
      "count": 274
    },
    {
      "cmd": "rampok2",
      "count": 266
    },
    {
      "cmd": "afk",
      "count": 200
    },
    {
      "cmd": "gift",
      "count": 159
    },
    {
      "cmd": "craft",
      "count": 120
    },
    {
      "cmd": "carikarakter",
      "count": 100
    },
    {
      "cmd": "youtuber",
      "count": 94
    }
  ],
  "ratingAvg": "8.3",
  "ratingTotal": 7,
  "uptimeSeconds": 61,
  "lastUpdated": 1774604207583
}