{
  "botName": "🍄 𝗔𝗹𝘆𝗮 𝗠𝗗",
  "totalUsers": 972,
  "totalGroups": 36,
  "totalFeatures": 3494,
  "totalCmd": 742,
  "totalChat": 742,
  "topCommands": [
    {
      "cmd": "afk",
      "count": 36
    },
    {
      "cmd": "me",
      "count": 28
    },
    {
      "cmd": "ranked",
      "count": 26
    },
    {
      "cmd": "rampok2",
      "count": 23
    },
    {
      "cmd": "tes",
      "count": 21
    },
    {
      "cmd": "updatealya",
      "count": 21
    },
    {
      "cmd": "playmoba",
      "count": 18
    },
    {
      "cmd": "removebg",
      "count": 16
    },
    {
      "cmd": "atm",
      "count": 11
    },
    {
      "cmd": "hd",
      "count": 11
    }
  ],
  "ratingAvg": "10.0",
  "ratingTotal": 5,
  "uptimeSeconds": 2462,
  "lastUpdated": 1773824185463
}